bin/__init__.py
dcmrtstruct2nii/__init__.py
dcmrtstruct2nii/adapters/__init__.py
dcmrtstruct2nii/adapters/convert/__init__.py
dcmrtstruct2nii/adapters/convert/dcmnormalize.py
dcmrtstruct2nii/adapters/convert/filenameconverter.py
dcmrtstruct2nii/adapters/convert/rtstructcontour2mask.py
dcmrtstruct2nii/adapters/input/__init__.py
dcmrtstruct2nii/adapters/input/abstractinputadapter.py
dcmrtstruct2nii/adapters/input/contours/__init__.py
dcmrtstruct2nii/adapters/input/contours/rtstructinputadapter.py
dcmrtstruct2nii/adapters/input/image/__init__.py
dcmrtstruct2nii/adapters/input/image/dcminputadapter.py
dcmrtstruct2nii/adapters/input/metadata/__init__.py
dcmrtstruct2nii/adapters/input/metadata/dcmmetadatainputadapter.py
dcmrtstruct2nii/adapters/output/__init__.py
dcmrtstruct2nii/adapters/output/abstractoutputadapter.py
dcmrtstruct2nii/adapters/output/niioutputadapter.py
dcmrtstruct2nii/cli/__init__.py
dcmrtstruct2nii/cli/convert.py
dcmrtstruct2nii/cli/dcmrtstruct2nii.py
dcmrtstruct2nii/cli/liststructs.py
dcmrtstruct2nii/cli/wrapper/__init__.py
dcmrtstruct2nii/cli/wrapper/patchedcommand.py
dcmrtstruct2nii/exceptions/__init__.py
dcmrtstruct2nii/exceptions/contouroutofboundsexception.py
dcmrtstruct2nii/exceptions/invalidfileformatexception.py
dcmrtstruct2nii/exceptions/pathdoesnotexistexception.py
dcmrtstruct2nii/exceptions/unsupportedtypeexception.py
dcmrtstruct2nii/facade/__init__.py
dcmrtstruct2nii/facade/dcmrtstruct2nii.py
dcmrtstruct2nii-1.0.18.dist-info/LICENSE
dcmrtstruct2nii-1.0.18.dist-info/METADATA
dcmrtstruct2nii-1.0.18.dist-info/WHEEL
dcmrtstruct2nii-1.0.18.dist-info/entry_points.txt
dcmrtstruct2nii-1.0.18.dist-info/top_level.txt
dcmrtstruct2nii-1.0.18.dist-info/RECORD
