Metadata-Version: 2.1
Name: dcmrtstruct2nii
Version: 1.0.18
Summary: Convert DICOM RT-Struct to nii
Home-page: https://github.com/Sikerdebaard/dcmrtstruct2nii
Author: Thomas Phil
Author-email: thomas@tphil.nl
License: UNKNOWN
Platform: UNKNOWN
Requires-Python: >=3.6
Requires-Dist: numpy (>=1.15.4)
Requires-Dist: pydicom (>=1.2.1)
Requires-Dist: scikit-image (>=0.14.1)
Requires-Dist: scipy (>=1.2.0)
Requires-Dist: SimpleITK (>=1.2.0)
Requires-Dist: cleo (>=0.7.2)
